graper/__init__.py
graper/env.py
graper/setting.py
graper/util.py
graper/db/__init__.py
graper/db/db.py
graper/db/db_mysql.py
graper/db/db_oracle.py
graper/db/db_oss.py
graper/db/db_redis.py
graper/db/db_sqlite.py
graper/db/util.py
graper/network/__init__.py
graper/network/downloader.py
graper/network/proxy.py
graper/network/request.py
graper/network/response.py
graper/spiders/__init__.py
graper/spiders/base.py
graper/spiders/batch_spider.py
graper/utils/__init__.py
graper/utils/log.py
graper/utils/message/__init__.py
graper/utils/message/dingtalk.py
graper-0.1.6.dist-info/LICENSE
graper-0.1.6.dist-info/METADATA
graper-0.1.6.dist-info/WHEEL
graper-0.1.6.dist-info/top_level.txt
graper-0.1.6.dist-info/RECORD
